{"version":"3.10.1","examples":[{"id":"./spec/requests/sessions_spec.rb[1:1:1:1]","description":"returns the logged in user","full_description":"Sessions POST /login with valid username and password returns the logged in user","status":"passed","file_path":"./spec/requests/sessions_spec.rb","line_number":8,"run_time":0.020204,"pending_message":null},{"id":"./spec/requests/sessions_spec.rb[1:1:1:2]","description":"sets the user ID in the session","full_description":"Sessions POST /login with valid username and password sets the user ID in the session","status":"passed","file_path":"./spec/requests/sessions_spec.rb","line_number":16,"run_time":0.005641,"pending_message":null},{"id":"./spec/requests/sessions_spec.rb[1:1:2:1]","description":"returns a 401 unauthorized response","full_description":"Sessions POST /login with invalid password returns a 401 unauthorized response","status":"passed","file_path":"./spec/requests/sessions_spec.rb","line_number":24,"run_time":0.004303,"pending_message":null},{"id":"./spec/requests/sessions_spec.rb[1:1:2:2]","description":"does not set the user ID in the session","full_description":"Sessions POST /login with invalid password does not set the user ID in the session","status":"passed","file_path":"./spec/requests/sessions_spec.rb","line_number":30,"run_time":0.004729,"pending_message":null},{"id":"./spec/requests/sessions_spec.rb[1:1:3:1]","description":"returns a 401 unauthorized response","full_description":"Sessions POST /login with invalid username returns a 401 unauthorized response","status":"passed","file_path":"./spec/requests/sessions_spec.rb","line_number":38,"run_time":0.00391,"pending_message":null},{"id":"./spec/requests/sessions_spec.rb[1:1:3:2]","description":"does not set the user ID in the session","full_description":"Sessions POST /login with invalid username does not set the user ID in the session","status":"passed","file_path":"./spec/requests/sessions_spec.rb","line_number":44,"run_time":0.003072,"pending_message":null},{"id":"./spec/requests/sessions_spec.rb[1:2:1]","description":"returns no content","full_description":"Sessions DELETE /logout returns no content","status":"passed","file_path":"./spec/requests/sessions_spec.rb","line_number":58,"run_time":0.009006,"pending_message":null},{"id":"./spec/requests/sessions_spec.rb[1:2:2]","description":"deletes the user ID from the session","full_description":"Sessions DELETE /logout deletes the user ID from the session","status":"passed","file_path":"./spec/requests/sessions_spec.rb","line_number":64,"run_time":0.005,"pending_message":null},{"id":"./spec/requests/users_spec.rb[1:1:1:1]","description":"creates a new user","full_description":"Users POST /signup with matching password confirmation creates a new user","status":"passed","file_path":"./spec/requests/users_spec.rb","line_number":9,"run_time":0.006452,"pending_message":null},{"id":"./spec/requests/users_spec.rb[1:1:1:2]","description":"saves the password as password_digest to allow authentication","full_description":"Users POST /signup with matching password confirmation saves the password as password_digest to allow authentication","status":"passed","file_path":"./spec/requests/users_spec.rb","line_number":13,"run_time":0.005319,"pending_message":null},{"id":"./spec/requests/users_spec.rb[1:1:1:3]","description":"saves the user id in the session","full_description":"Users POST /signup with matching password confirmation saves the user id in the session","status":"passed","file_path":"./spec/requests/users_spec.rb","line_number":19,"run_time":0.003667,"pending_message":null},{"id":"./spec/requests/users_spec.rb[1:1:1:4]","description":"returns the user as JSON","full_description":"Users POST /signup with matching password confirmation returns the user as JSON","status":"passed","file_path":"./spec/requests/users_spec.rb","line_number":25,"run_time":0.005532,"pending_message":null},{"id":"./spec/requests/users_spec.rb[1:1:2:1]","description":"does not save the user","full_description":"Users POST /signup with no matching password confirmation does not save the user","status":"passed","file_path":"./spec/requests/users_spec.rb","line_number":39,"run_time":0.007924,"pending_message":null},{"id":"./spec/requests/users_spec.rb[1:1:2:2]","description":"returns a 422 unprocessable entity response","full_description":"Users POST /signup with no matching password confirmation returns a 422 unprocessable entity response","status":"passed","file_path":"./spec/requests/users_spec.rb","line_number":43,"run_time":0.005302,"pending_message":null},{"id":"./spec/requests/users_spec.rb[1:2:1]","description":"returns the first user when the first user is logged in","full_description":"Users GET /me returns the first user when the first user is logged in","status":"passed","file_path":"./spec/requests/users_spec.rb","line_number":56,"run_time":0.018641,"pending_message":null},{"id":"./spec/requests/users_spec.rb[1:2:2]","description":"returns the second user when the second user is logged in","full_description":"Users GET /me returns the second user when the second user is logged in","status":"passed","file_path":"./spec/requests/users_spec.rb","line_number":65,"run_time":0.013498,"pending_message":null},{"id":"./spec/requests/users_spec.rb[1:2:3]","description":"returns a 401 unauthorized response when no user is logged in","full_description":"Users GET /me returns a 401 unauthorized response when no user is logged in","status":"passed","file_path":"./spec/requests/users_spec.rb","line_number":74,"run_time":0.005686,"pending_message":null}],"summary":{"duration":0.130429,"example_count":17,"failure_count":0,"pending_count":0,"errors_outside_of_examples_count":0},"summary_line":"17 examples, 0 failures"}